aud/__init__.py
aud/__main__.py
aud/aud.py
aud/cli.py
aud/exceptions.py
aud/py.typed
aud/core/__init__.py
aud/core/models.py
aud/core/plan.py
aud/core/adapters/__init__.py
aud/core/adapters/audio.py
aud/core/adapters/convert.py
aud/core/adapters/filesystem.py
aud/core/operations/__init__.py
aud/core/operations/archive.py
aud/core/operations/base.py
aud/core/operations/files.py
aud/core/operations/names.py
aud/core/operations/audio/base.py
aud/core/operations/audio/convert.py
aud/core/operations/audio/effects.py
aud/core/selection/composite.py
aud/core/selection/extensions.py
aud/core/selection/listing.py
aud/core/selection/policy.py
aud/core/selection/scanner.py
aud-2.0.1.dist-info/METADATA
aud-2.0.1.dist-info/WHEEL
aud-2.0.1.dist-info/entry_points.txt
aud-2.0.1.dist-info/licenses/LICENSE
aud-2.0.1.dist-info/RECORD
