Metadata-Version: 2.4
Name: aud
Version: 2.0.1
Summary: A tool for batch audio file processing
Project-URL: Homepage, https://github.com/zdhoward/aud
Project-URL: Documentation, https://github.com/zdhoward/aud/blob/master/README.md
Project-URL: Repository, https://github.com/zdhoward/aud
Project-URL: Issues, https://github.com/zdhoward/aud/issues
Author-email: Zach Howard <3210164+zdhoward@users.noreply.github.com>
License: MIT
License-File: LICENSE
Keywords: audio,batch,conversion,ffmpeg,processing
Classifier: Programming Language :: Python :: 3
Classifier: Programming Language :: Python :: 3.10
Classifier: Programming Language :: Python :: 3.11
Classifier: Programming Language :: Python :: 3.12
Requires-Python: >=3.10
Requires-Dist: colorama>=0.4.6
Requires-Dist: pydub>=0.25.1
Provides-Extra: cli
Requires-Dist: click>=8.1.0; extra == 'cli'
Requires-Dist: questionary>=2.0.0; extra == 'cli'
Requires-Dist: rich>=13.0.0; extra == 'cli'
Provides-Extra: dev
Requires-Dist: black>=24.0.0; extra == 'dev'
Requires-Dist: mypy>=1.5.0; extra == 'dev'
Requires-Dist: pre-commit>=3.5.0; extra == 'dev'
Requires-Dist: pytest-cov>=4.1.0; extra == 'dev'
Requires-Dist: pytest>=7.4.0; extra == 'dev'
Requires-Dist: ruff>=0.1.0; extra == 'dev'
